[
  {
    "stokno": "STKTF2387",
    "uruncinsi": "NOTEBOOK",
    "marka": "CASPER",
    "model": "A580",
    "serino": "1864886464",
    "islemci": "İ9 13100",
    "ram": "16 GB",
    "hdd": "512 M2 SSD",
    "ekrankart": "RTX 4060",
    "ekranboyutu": "15,6",
    "kozmetik": "10",
    "aciklama": "ÜRÜN TERTEMİZ KUTULU FATURALI VE GARANTİLİ",
    "alinan": "2025-01-10",
    "satilan": "2025-07-12",
    "alisfiyati": "50000",
    "satisfiyati": "35000",
    "notlar": "",
    "fotolar": [
      "/upload/Ekrangrnts2025-07-11003311-1752190289370.png"
    ],
    "vitrinfoto": ""
  },
  {
    "stokno": "STKTR2472",
    "uruncinsi": "NOTEBOOK",
    "marka": "MONSTER",
    "model": "ABRA A7",
    "serino": "5161684843332",
    "islemci": "İ9 13100",
    "ram": "64 GB",
    "hdd": "512 M2 SSD",
    "ekrankart": "RTX 4060",
    "ekranboyutu": "15,6",
    "kozmetik": "10",
    "aciklama": "ÜRÜN TERTEMİZ KUTULU FATURALI VE GARANTİLİ",
    "alinan": "2025-01-10",
    "satilan": "2025-07-11",
    "alisfiyati": "20000",
    "satisfiyati": "30000",
    "notlar": "",
    "fotolar": [],
    "vitrinfoto": ""
  },
  {
    "stokno": "STKYP5516",
    "uruncinsi": "NOTEBOOK",
    "marka": "MONSTER",
    "model": "ABRA A5",
    "serino": "516168484864",
    "islemci": "İ5 10200U",
    "ram": "16 GB",
    "hdd": "1 TB M2 SSD",
    "ekrankart": "RTX 3050",
    "ekranboyutu": "15,6",
    "kozmetik": "10",
    "aciklama": "ÜRÜN TERTEMİZ KUTULU FATURALI VE GARANTİLİ",
    "alinan": "2025-01-10",
    "satilan": "2025-01-15",
    "alisfiyati": "100000",
    "satisfiyati": "20000",
    "notlar": "",
    "fotolar": [],
    "vitrinfoto": ""
  },
  {
    "stokno": "STKAB1234",
    "uruncinsi": "NOTEBOOK",
    "marka": "HP",
    "model": "PAVILION",
    "serino": "HPG456789",
    "islemci": "İ7 12700H",
    "ram": "16 GB",
    "hdd": "512 M2 SSD",
    "ekrankart": "RTX 3060",
    "ekranboyutu": "15,6",
    "kozmetik": "9",
    "aciklama": "GAMING NOTEBOOK, TERTEMIZ DURUMDA",
    "alinan": "2025-01-12",
    "satilan": "2025-07-12",
    "alisfiyati": "35000",
    "satisfiyati": "42000",
    "notlar": "Stokta 1 adet",
    "fotolar": [
      "/upload/Xiaomi-Mi-Notebook-Pro-Enhanced-Edition-i5-10210U-8GB-512GB-Gray-906826--1752269456200.jpg"
    ],
    "vitrinfoto": ""
  },
  {
    "stokno": "STKCD5678",
    "uruncinsi": "DESKTOP",
    "marka": "CUSTOM",
    "model": "GAMING PC",
    "serino": "CUSTOM001",
    "islemci": "İ9 13900K",
    "ram": "32 GB",
    "hdd": "1 TB M2 SSD",
    "ekrankart": "RTX 4070",
    "ekranboyutu": "24",
    "kozmetik": "10",
    "aciklama": "YÜKSEK PERFORMANS GAMING PC",
    "alinan": "2025-01-13",
    "satilan": "2025-07-12",
    "alisfiyati": "60000",
    "satisfiyati": "75000",
    "notlar": "Özel yapım",
    "fotolar": [],
    "vitrinfoto": ""
  },
  {
    "stokno": "STKEF9012",
    "uruncinsi": "TABLET",
    "marka": "SAMSUNG",
    "model": "GALAXY TAB S9",
    "serino": "SM789012",
    "islemci": "SNAPDRAGON 8 GEN 2",
    "ram": "8 GB",
    "hdd": "128 GB",
    "ekrankart": "ADRENO 740",
    "ekranboyutu": "11",
    "kozmetik": "10",
    "aciklama": "YENI TABLET, KUTULU VE GARANTİLİ",
    "alinan": "2025-01-14",
    "satilan": "",
    "alisfiyati": "25000",
    "satisfiyati": "32000",
    "notlar": "",
    "fotolar": [],
    "vitrinfoto": ""
  },
  {
    "stokno": "STKGH3456",
    "uruncinsi": "NOTEBOOK",
    "marka": "ASUS",
    "model": "VIVOBOOK",
    "serino": "ASUS345678",
    "islemci": "İ5 1235U",
    "ram": "8 GB",
    "hdd": "256 M2 SSD",
    "ekrankart": "INTEL IRIS XE",
    "ekranboyutu": "14",
    "kozmetik": "8",
    "aciklama": "GÜNLÜK KULLANIM İÇİN IDEAL",
    "alinan": "2025-01-15",
    "satilan": "",
    "alisfiyati": "18000",
    "satisfiyati": "25000",
    "notlar": "Hafif kullanım izleri",
    "fotolar": [],
    "vitrinfoto": ""
  },
  {
    "stokno": "STKIJ7890",
    "uruncinsi": "TELEFON",
    "marka": "IPHONE",
    "model": "14 PRO",
    "serino": "IPHONE789",
    "islemci": "A16 BIONIC",
    "ram": "6 GB",
    "hdd": "128 GB",
    "ekrankart": "A16 GPU",
    "ekranboyutu": "6,1",
    "kozmetik": "9",
    "aciklama": "KUTULU VE GARANTİLİ IPHONE",
    "alinan": "2025-01-16",
    "satilan": "",
    "alisfiyati": "40000",
    "satisfiyati": "48000",
    "notlar": "Orjinal aksesuar",
    "fotolar": [],
    "vitrinfoto": ""
  },
  {
    "stokno": "STKKL1234",
    "uruncinsi": "NOTEBOOK",
    "marka": "LENOVO",
    "model": "THINKPAD",
    "serino": "LENOVO123",
    "islemci": "İ7 1260P",
    "ram": "16 GB",
    "hdd": "512 M2 SSD",
    "ekrankart": "INTEL IRIS XE",
    "ekranboyutu": "14",
    "kozmetik": "10",
    "aciklama": "İŞ NOTEBOOK, PROFESYONEL KULLANIM",
    "alinan": "2025-01-17",
    "satilan": "",
    "alisfiyati": "30000",
    "satisfiyati": "38000",
    "notlar": "KURUMSAL GARANTİ",
    "fotolar": [],
    "vitrinfoto": ""
  },
  {
    "stokno": "STKMN5678",
    "uruncinsi": "TABLET",
    "marka": "IPAD",
    "model": "AIR 5",
    "serino": "IPAD567890",
    "islemci": "M1 CHIP",
    "ram": "8 GB",
    "hdd": "256 GB",
    "ekrankart": "M1 GPU",
    "ekranboyutu": "10,9",
    "kozmetik": "10",
    "aciklama": "APPLE TABLET, YARATICI ÇALIŞMALAR İÇİN",
    "alinan": "2025-01-18",
    "satilan": "",
    "alisfiyati": "28000",
    "satisfiyati": "35000",
    "notlar": "Apple Pencil dahil",
    "fotolar": [],
    "vitrinfoto": ""
  },
  {
    "stokno": "STKOP9012",
    "uruncinsi": "DESKTOP",
    "marka": "INTEL",
    "model": "NUC",
    "serino": "INTEL901",
    "islemci": "İ5 1240P",
    "ram": "8 GB",
    "hdd": "256 M2 SSD",
    "ekrankart": "INTEL IRIS XE",
    "ekranboyutu": "0",
    "kozmetik": "10",
    "aciklama": "MINI PC, OFIS KULLANIMI",
    "alinan": "2025-01-19",
    "satilan": "",
    "alisfiyati": "15000",
    "satisfiyati": "22000",
    "notlar": "Kompakt tasarım",
    "fotolar": [],
    "vitrinfoto": ""
  },
  {
    "stokno": "STKQR3456",
    "uruncinsi": "NOTEBOOK",
    "marka": "ACER",
    "model": "ASPIRE",
    "serino": "ACER345678",
    "islemci": "İ3 1115G4",
    "ram": "8 GB",
    "hdd": "256 M2 SSD",
    "ekrankart": "INTEL UHD",
    "ekranboyutu": "15,6",
    "kozmetik": "7",
    "aciklama": "ÖĞRENCI NOTEBOOK, UYGUN FİYAT",
    "alinan": "2025-01-20",
    "satilan": "",
    "alisfiyati": "12000",
    "satisfiyati": "18000",
    "notlar": "Öğrencilere uygun",
    "fotolar": [],
    "vitrinfoto": ""
  },
  {
    "stokno": "STKST7890",
    "uruncinsi": "TELEFON",
    "marka": "SAMSUNG",
    "model": "GALAXY S23",
    "serino": "SM789012",
    "islemci": "SNAPDRAGON 8 GEN 2",
    "ram": "8 GB",
    "hdd": "128 GB",
    "ekrankart": "ADRENO 740",
    "ekranboyutu": "6,1",
    "kozmetik": "9",
    "aciklama": "FLAGHIP ANDROID TELEFON",
    "alinan": "2025-01-21",
    "satilan": "",
    "alisfiyati": "32000",
    "satisfiyati": "40000",
    "notlar": "Wireless şarj",
    "fotolar": [],
    "vitrinfoto": ""
  },
  {
    "stokno": "STKUV1234",
    "uruncinsi": "NOTEBOOK",
    "marka": "DELL",
    "model": "INSPIRON",
    "serino": "DELL123456",
    "islemci": "İ5 1235U",
    "ram": "8 GB",
    "hdd": "512 M2 SSD",
    "ekrankart": "INTEL IRIS XE",
    "ekranboyutu": "15,6",
    "kozmetik": "8",
    "aciklama": "GÜNLÜK KULLANIM NOTEBOOK",
    "alinan": "2025-01-22",
    "satilan": "",
    "alisfiyati": "20000",
    "satisfiyati": "28000",
    "notlar": "Temiz durumda",
    "fotolar": [],
    "vitrinfoto": ""
  },
  {
    "stokno": "STKWX5678",
    "uruncinsi": "TABLET",
    "marka": "XIAOMI",
    "model": "PAD 5",
    "serino": "XIAOMI567",
    "islemci": "SNAPDRAGON 860",
    "ram": "6 GB",
    "hdd": "128 GB",
    "ekrankart": "ADRENO 640",
    "ekranboyutu": "11",
    "kozmetik": "9",
    "aciklama": "UYGUN FİYAT TABLET",
    "alinan": "2025-01-23",
    "satilan": "",
    "alisfiyati": "18000",
    "satisfiyati": "25000",
    "notlar": "Stylus kalem dahil",
    "fotolar": [],
    "vitrinfoto": ""
  },
  {
    "stokno": "STKYZ9012",
    "uruncinsi": "NOTEBOOK",
    "marka": "MSI",
    "model": "GAMING",
    "serino": "MSI901234",
    "islemci": "İ7 12700H",
    "ram": "16 GB",
    "hdd": "1 TB M2 SSD",
    "ekrankart": "RTX 3070",
    "ekranboyutu": "15,6",
    "kozmetik": "10",
    "aciklama": "YÜKSEK PERFORMANS GAMING",
    "alinan": "2025-01-24",
    "satilan": "",
    "alisfiyati": "45000",
    "satisfiyati": "55000",
    "notlar": "RGB klavye",
    "fotolar": [],
    "vitrinfoto": ""
  },
  {
    "stokno": "STKAB3456",
    "uruncinsi": "DESKTOP",
    "marka": "HP",
    "model": "ELITE",
    "serino": "HP345678",
    "islemci": "İ5 12400",
    "ram": "16 GB",
    "hdd": "512 M2 SSD",
    "ekrankart": "INTEL UHD",
    "ekranboyutu": "22",
    "kozmetik": "9",
    "aciklama": "OFIS DESKTOP, PROFESYONEL",
    "alinan": "2025-01-25",
    "satilan": "",
    "alisfiyati": "25000",
    "satisfiyati": "32000",
    "notlar": "Monitör dahil",
    "fotolar": [],
    "vitrinfoto": ""
  },
  {
    "stokno": "STKCD7890",
    "uruncinsi": "NOTEBOOK",
    "marka": "ALIENWARE",
    "model": "M15",
    "serino": "ALIEN789",
    "islemci": "İ9 12900H",
    "ram": "32 GB",
    "hdd": "1 TB M2 SSD",
    "ekrankart": "RTX 4080",
    "ekranboyutu": "15,6",
    "kozmetik": "10",
    "aciklama": "ULTRA HIGH-END GAMING",
    "alinan": "2025-01-26",
    "satilan": "",
    "alisfiyati": "80000",
    "satisfiyati": "95000",
    "notlar": "Özel seri",
    "fotolar": [],
    "vitrinfoto": ""
  },
  {
    "stokno": "STKEF1234",
    "uruncinsi": "TELEFON",
    "marka": "XIAOMI",
    "model": "REDMI NOTE 12",
    "serino": "REDMI123",
    "islemci": "SNAPDRAGON 685",
    "ram": "6 GB",
    "hdd": "128 GB",
    "ekrankart": "ADRENO 610",
    "ekranboyutu": "6,67",
    "kozmetik": "8",
    "aciklama": "EKONOMIK ANDROID TELEFON",
    "alinan": "2025-01-27",
    "satilan": "",
    "alisfiyati": "8000",
    "satisfiyati": "12000",
    "notlar": "Hızlı şarj",
    "fotolar": [],
    "vitrinfoto": ""
  },
  {
    "stokno": "STKGH5678",
    "uruncinsi": "NOTEBOOK",
    "marka": "CASPER",
    "model": "EXCALIBUR",
    "serino": "CASPER567",
    "islemci": "İ7 11800H",
    "ram": "16 GB",
    "hdd": "512 M2 SSD",
    "ekrankart": "RTX 3060",
    "ekranboyutu": "15,6",
    "kozmetik": "9",
    "aciklama": "TÜRK MARKASI GAMING",
    "alinan": "2025-01-28",
    "satilan": "",
    "alisfiyati": "35000",
    "satisfiyati": "42000",
    "notlar": "Yerel garanti",
    "fotolar": [],
    "vitrinfoto": ""
  },
  {
    "stokno": "STKIJ9012",
    "uruncinsi": "TABLET",
    "marka": "LENOVO",
    "model": "TAB P11",
    "serino": "LENOVO901",
    "islemci": "HELIO G90T",
    "ram": "4 GB",
    "hdd": "64 GB",
    "ekrankart": "IMG 9XM-HP8",
    "ekranboyutu": "11",
    "kozmetik": "8",
    "aciklama": "UYGUN FİYAT TABLET",
    "alinan": "2025-01-29",
    "satilan": "",
    "alisfiyati": "12000",
    "satisfiyati": "18000",
    "notlar": "Aile tablet",
    "fotolar": [],
    "vitrinfoto": ""
  },
  {
    "stokno": "STKKL3456",
    "uruncinsi": "NOTEBOOK",
    "marka": "ASUS",
    "model": "ROG STRIX",
    "serino": "ASUS234567",
    "islemci": "İ7 12700H",
    "ram": "16 GB",
    "hdd": "1 TB M2 SSD",
    "ekrankart": "RTX 3070 Ti",
    "ekranboyutu": "15,6",
    "kozmetik": "10",
    "aciklama": "PROFESYONEL GAMING NOTEBOOK",
    "alinan": "2025-01-30",
    "satilan": "",
    "alisfiyati": "48000",
    "satisfiyati": "58000",
    "notlar": "ROG serisi",
    "fotolar": [],
    "vitrinfoto": ""
  },
  {
    "stokno": "STKMN7890",
    "uruncinsi": "TABLET",
    "marka": "HUAWEI",
    "model": "MATEPAD",
    "serino": "HUAWEI789",
    "islemci": "KIRIN 820",
    "ram": "6 GB",
    "hdd": "128 GB",
    "ekrankart": "MALI G57",
    "ekranboyutu": "10,4",
    "kozmetik": "9",
    "aciklama": "HUAWEI TABLET, PREMIUM",
    "alinan": "2025-01-31",
    "satilan": "",
    "alisfiyati": "15000",
    "satisfiyati": "22000",
    "notlar": "M-Pencil dahil",
    "fotolar": [],
    "vitrinfoto": ""
  }
]